{"click-Positions": [[416, 6], [166, 473]], "resolution": [480, 856, 3], "filename": "bild146.jpg"}
{"click-Positions": [[514, 12], [433, 468]], "resolution": [480, 856, 3], "filename": "bild208.jpg"}
{"click-Positions": [[511, 6], [422, 474]], "resolution": [480, 856, 3], "filename": "bild215.jpg"}
{"click-Positions": [[344, 6], [192, 474]], "resolution": [480, 856, 3], "filename": "bild187.jpg"}
{"click-Positions": [[534, 6], [404, 475]], "resolution": [480, 856, 3], "filename": "bild205.jpg"}
{"click-Positions": [[486, 3], [179, 474]], "resolution": [480, 856, 3], "filename": "bild83.jpg"}
{"click-Positions": [[498, 7], [411, 474]], "resolution": [480, 856, 3], "filename": "bild210.jpg"}
{"click-Positions": [[301, 5], [209, 477]], "resolution": [480, 856, 3], "filename": "bild239.jpg"}
{"click-Positions": [[200, 7], [98, 475]], "resolution": [480, 856, 3], "filename": "bild257.jpg"}
{"click-Positions": [[423, 5], [154, 477]], "resolution": [480, 856, 3], "filename": "bild137.jpg"}
{"click-Positions": [[448, 5], [279, 474]], "resolution": [480, 856, 3], "filename": "bild196.jpg"}
{"click-Positions": [[439, 475]], "resolution": [480, 856, 3], "filename": "bild216.jpg"}
{"click-Positions": [[382, 8], [5, 440]], "resolution": [480, 856, 3], "filename": "bild167.jpg"}
{"click-Positions": [[815, 6], [790, 469]], "resolution": [480, 856, 3], "filename": "bild10.jpg"}
{"click-Positions": [[259, 6], [163, 474]], "resolution": [480, 856, 3], "filename": "bild252.jpg"}
{"click-Positions": [[421, 8], [113, 475]], "resolution": [480, 856, 3], "filename": "bild143.jpg"}
{"click-Positions": [[475, 4], [279, 475]], "resolution": [480, 856, 3], "filename": "bild35.jpg"}
{"click-Positions": [[388, 6], [289, 477]], "resolution": [480, 856, 3], "filename": "bild227.jpg"}
{"click-Positions": [[219, 6], [116, 475]], "resolution": [480, 856, 3], "filename": "bild254.jpg"}
{"click-Positions": [[590, 6], [380, 474]], "resolution": [480, 856, 3], "filename": "bild48.jpg"}
{"click-Positions": [], "resolution": [480, 856, 3], "filename": "bild151.jpg"}
{"click-Positions": [], "resolution": [480, 856, 3], "filename": "bild67.jpg"}
{"click-Positions": [[469, 7], [207, 475]], "resolution": [480, 856, 3], "filename": "bild84.jpg"}
{"click-Positions": [[288, 7], [2, 413]], "resolution": [480, 856, 3], "filename": "bild62.jpg"}
{"click-Positions": [[233, 6], [3, 369]], "resolution": [480, 856, 3], "filename": "bild64.jpg"}
{"click-Positions": [[439, 8], [185, 477]], "resolution": [480, 856, 3], "filename": "bild104.jpg"}
{"click-Positions": [[456, 8], [170, 474]], "resolution": [480, 856, 3], "filename": "bild126.jpg"}
{"click-Positions": [[401, 4], [255, 474]], "resolution": [480, 856, 3], "filename": "bild200.jpg"}
{"click-Positions": [[407, 4], [408, 4]], "resolution": [480, 856, 3], "filename": "bild138.jpg"}
{"click-Positions": [[539, 6], [344, 456]], "resolution": [480, 856, 3], "filename": "bild37.jpg"}
{"click-Positions": [[438, 5], [184, 475]], "resolution": [480, 856, 3], "filename": "bild106.jpg"}
{"click-Positions": [[517, 4], [383, 473]], "resolution": [480, 856, 3], "filename": "bild181.jpg"}
{"click-Positions": [[488, 5], [410, 474]], "resolution": [480, 856, 3], "filename": "bild223.jpg"}
{"click-Positions": [[401, 6], [244, 474]], "resolution": [480, 856, 3], "filename": "bild198.jpg"}
{"click-Positions": [[361, 5], [192, 472]], "resolution": [480, 856, 3], "filename": "bild189.jpg"}
{"click-Positions": [[429, 4], [326, 470]], "resolution": [480, 856, 3], "filename": "bild225.jpg"}
{"click-Positions": [[329, 6], [309, 474]], "resolution": [480, 856, 3], "filename": "bild155.jpg"}
{"click-Positions": [[605, 7], [432, 472]], "resolution": [480, 856, 3], "filename": "bild31.jpg"}
{"click-Positions": [[386, 6], [159, 472]], "resolution": [480, 856, 3], "filename": "bild72.jpg"}
{"click-Positions": [[427, 5], [166, 475]], "resolution": [480, 856, 3], "filename": "bild113.jpg"}
{"click-Positions": [[445, 6], [177, 474]], "resolution": [480, 856, 3], "filename": "bild112.jpg"}
{"click-Positions": [[831, 8], [802, 471]], "resolution": [480, 856, 3], "filename": "bild202.jpg"}
{"click-Positions": [[386, 6], [239, 457]], "resolution": [480, 856, 3], "filename": "bild172.jpg"}
{"click-Positions": [[491, 6], [285, 475]], "resolution": [480, 856, 3], "filename": "bild36.jpg"}
{"click-Positions": [[577, 9], [363, 468]], "resolution": [480, 856, 3], "filename": "bild52.jpg"}
{"click-Positions": [[624, 7], [412, 475]], "resolution": [480, 856, 3], "filename": "bild49.jpg"}
{"click-Positions": [[563, 7], [336, 474]], "resolution": [480, 856, 3], "filename": "bild59.jpg"}
{"click-Positions": [[631, 6], [453, 475]], "resolution": [480, 856, 3], "filename": "bild30.jpg"}
{"click-Positions": [[499, 6], [401, 472]], "resolution": [480, 856, 3], "filename": "bild212.jpg"}
{"click-Positions": [[275, 7], [177, 475]], "resolution": [480, 856, 3], "filename": "bild245.jpg"}
{"click-Positions": [[459, 6], [373, 470]], "resolution": [480, 856, 3], "filename": "bild224.jpg"}
{"click-Positions": [[463, 15], [229, 478]], "resolution": [480, 856, 3], "filename": "bild87.jpg"}
{"click-Positions": [[467, 6], [175, 474]], "resolution": [480, 856, 3], "filename": "bild118.jpg"}
{"click-Positions": [[416, 7], [252, 469]], "resolution": [480, 856, 3], "filename": "bild184.jpg"}
{"click-Positions": [[433, 6], [227, 474]], "resolution": [480, 856, 3], "filename": "bild191.jpg"}
{"click-Positions": [[355, 6], [334, 471]], "resolution": [480, 856, 3], "filename": "bild88.jpg"}
{"click-Positions": [[436, 8], [161, 474]], "resolution": [480, 856, 3], "filename": "bild132.jpg"}
{"click-Positions": [[502, 7], [426, 470]], "resolution": [480, 856, 3], "filename": "bild209.jpg"}
{"click-Positions": [[430, 6], [173, 476]], "resolution": [480, 856, 3], "filename": "bild121.jpg"}
{"click-Positions": [[481, 6]], "resolution": [480, 856, 3], "filename": "bild68.jpg"}
{"click-Positions": [[441, 6], [164, 474]], "resolution": [480, 856, 3], "filename": "bild136.jpg"}
{"click-Positions": [[552, 6], [367, 475]], "resolution": [480, 856, 3], "filename": "bild169.jpg"}
{"click-Positions": [[322, 6], [123, 474]], "resolution": [480, 856, 3], "filename": "bild176.jpg"}
{"click-Positions": [[418, 6], [141, 475]], "resolution": [480, 856, 3], "filename": "bild141.jpg"}
{"click-Positions": [[414, 8], [101, 473]], "resolution": [480, 856, 3], "filename": "bild147.jpg"}
{"click-Positions": [[812, 5], [789, 474]], "resolution": [480, 856, 3], "filename": "bild12.jpg"}
{"click-Positions": [[540, 7], [347, 475]], "resolution": [480, 856, 3], "filename": "bild57.jpg"}
{"click-Positions": [[519, 6], [233, 473]], "resolution": [480, 856, 3], "filename": "bild91.jpg"}
{"click-Positions": [[531, 4], [431, 473]], "resolution": [480, 856, 3], "filename": "bild219.jpg"}
{"click-Positions": [[199, 9], [2, 326]], "resolution": [480, 856, 3], "filename": "bild160.jpg"}
{"click-Positions": [[423, 6], [162, 474]], "resolution": [480, 856, 3], "filename": "bild114.jpg"}
{"click-Positions": [[288, 8], [4, 315]], "resolution": [480, 856, 3], "filename": "bild148.jpg"}
{"click-Positions": [[333, 6], [314, 474]], "resolution": [480, 856, 3], "filename": "bild144.jpg"}
{"click-Positions": [[326, 4]], "resolution": [480, 856, 3], "filename": "bild173.jpg"}
{"click-Positions": [[364, 6], [263, 474]], "resolution": [480, 856, 3], "filename": "bild229.jpg"}
{"click-Positions": [[410, 6], [160, 468]], "resolution": [480, 856, 3], "filename": "bild74.jpg"}
{"click-Positions": [[430, 4], [162, 475]], "resolution": [480, 856, 3], "filename": "bild131.jpg"}
{"click-Positions": [[531, 5], [344, 475]], "resolution": [480, 856, 3], "filename": "bild54.jpg"}
{"click-Positions": [[501, 8], [167, 473]], "resolution": [480, 856, 3], "filename": "bild61.jpg"}
{"click-Positions": [[601, 6], [338, 472]], "resolution": [480, 856, 3], "filename": "bild40.jpg"}
{"click-Positions": [[502, 8], [310, 442]], "resolution": [480, 856, 3], "filename": "bild171.jpg"}
{"click-Positions": [[531, 6], [401, 454]], "resolution": [480, 856, 3], "filename": "bild21.jpg"}
{"click-Positions": [[426, 6], [166, 474]], "resolution": [480, 856, 3], "filename": "bild130.jpg"}
{"click-Positions": [[562, 8], [404, 422]], "resolution": [480, 856, 3], "filename": "bild32.jpg"}
{"click-Positions": [[368, 6], [350, 443]], "resolution": [480, 856, 3], "filename": "bild66.jpg"}
{"click-Positions": [[683, 6], [538, 444]], "resolution": [480, 856, 3], "filename": "bild17.jpg"}
{"click-Positions": [[463, 7], [174, 474]], "resolution": [480, 856, 3], "filename": "bild108.jpg"}
{"click-Positions": [[531, 6], [531, 6]], "resolution": [480, 856, 3], "filename": "bild207.jpg"}
{"click-Positions": [[503, 9], [242, 472]], "resolution": [480, 856, 3], "filename": "bild92.jpg"}
{"click-Positions": [[735, 4], [596, 460]], "resolution": [480, 856, 3], "filename": "bild16.jpg"}
{"click-Positions": [[445, 7], [166, 475]], "resolution": [480, 856, 3], "filename": "bild128.jpg"}
{"click-Positions": [[417, 8], [192, 450]], "resolution": [480, 856, 3], "filename": "bild178.jpg"}
{"click-Positions": [[653, 6], [481, 472]], "resolution": [480, 856, 3], "filename": "bild26.jpg"}
{"click-Positions": [[454, 9], [276, 470]], "resolution": [480, 856, 3], "filename": "bild192.jpg"}
{"click-Positions": [[416, 7], [184, 474]], "resolution": [480, 856, 3], "filename": "bild80.jpg"}
{"click-Positions": [[291, 10], [194, 475]], "resolution": [480, 856, 3], "filename": "bild241.jpg"}
{"click-Positions": [[342, 2], [321, 473]], "resolution": [480, 856, 3], "filename": "bild133.jpg"}
{"click-Positions": [[623, 6], [483, 466]], "resolution": [480, 856, 3], "filename": "bild18.jpg"}
{"click-Positions": [[166, 9], [5, 309]], "resolution": [480, 856, 3], "filename": "bild153.jpg"}
{"click-Positions": [], "resolution": [480, 856, 3], "filename": "bild163.jpg"}
{"click-Positions": [[779, 5], [779, 5]], "resolution": [480, 856, 3], "filename": "bild15.jpg"}
{"click-Positions": [], "resolution": [480, 856, 3], "filename": "bild75.jpg"}
{"click-Positions": [[288, 6], [191, 474]], "resolution": [480, 856, 3], "filename": "bild248.jpg"}
{"click-Positions": [[556, 5], [374, 465]], "resolution": [480, 856, 3], "filename": "bild47.jpg"}
{"click-Positions": [[294, 7], [200, 475]], "resolution": [480, 856, 3], "filename": "bild240.jpg"}
{"click-Positions": [[463, 7], [307, 475]], "resolution": [480, 856, 3], "filename": "bild195.jpg"}
{"click-Positions": [[606, 9], [231, 469]], "resolution": [480, 856, 3], "filename": "bild158.jpg"}
{"click-Positions": [[421, 11], [184, 474]], "resolution": [480, 856, 3], "filename": "bild81.jpg"}
{"click-Positions": [[204, 6], [101, 474]], "resolution": [480, 856, 3], "filename": "bild259.jpg"}
{"click-Positions": [[447, 5], [206, 473]], "resolution": [480, 856, 3], "filename": "bild96.jpg"}
{"click-Positions": [[348, 8], [206, 474]], "resolution": [480, 856, 3], "filename": "bild186.jpg"}
{"click-Positions": [[505, 8], [424, 472]], "resolution": [480, 856, 3], "filename": "bild221.jpg"}
{"click-Positions": [[315, 6], [213, 474]], "resolution": [480, 856, 3], "filename": "bild235.jpg"}
{"click-Positions": [], "resolution": [480, 856, 3], "filename": "bild65.jpg"}
{"click-Positions": [[447, 7], [208, 473]], "resolution": [480, 856, 3], "filename": "bild95.jpg"}
{"click-Positions": [[511, 6], [385, 462]], "resolution": [480, 856, 3], "filename": "bild180.jpg"}
{"click-Positions": [[280, 7], [184, 474]], "resolution": [480, 856, 3], "filename": "bild247.jpg"}
{"click-Positions": [[470, 10], [202, 477]], "resolution": [480, 856, 3], "filename": "bild102.jpg"}
{"click-Positions": [[503, 6], [249, 471]], "resolution": [480, 856, 3], "filename": "bild89.jpg"}
{"click-Positions": [[581, 5], [370, 474]], "resolution": [480, 856, 3], "filename": "bild38.jpg"}
{"click-Positions": [[424, 7], [42, 471]], "resolution": [480, 856, 3], "filename": "bild159.jpg"}
{"click-Positions": [[614, 6], [420, 443]], "resolution": [480, 856, 3], "filename": "bild51.jpg"}
{"click-Positions": [[431, 8], [294, 460]], "resolution": [480, 856, 3], "filename": "bild201.jpg"}
{"click-Positions": [[519, 5], [494, 472]], "resolution": [480, 856, 3], "filename": "bild0.jpg"}
{"click-Positions": [[426, 7], [160, 474]], "resolution": [480, 856, 3], "filename": "bild124.jpg"}
{"click-Positions": [[374, 5], [356, 422]], "resolution": [480, 856, 3], "filename": "bild33.jpg"}
{"click-Positions": [[424, 6], [130, 471]], "resolution": [480, 856, 3], "filename": "bild142.jpg"}
{"click-Positions": [[532, 7], [533, 7]], "resolution": [480, 856, 3], "filename": "bild218.jpg"}
{"click-Positions": [[320, 7], [221, 475]], "resolution": [480, 856, 3], "filename": "bild232.jpg"}
{"click-Positions": [[554, 8], [369, 470]], "resolution": [480, 856, 3], "filename": "bild170.jpg"}
{"click-Positions": [[406, 6], [139, 474]], "resolution": [480, 856, 3], "filename": "bild140.jpg"}
{"click-Positions": [[621, 6], [417, 474]], "resolution": [480, 856, 3], "filename": "bild157.jpg"}
{"click-Positions": [[522, 8], [428, 474]], "resolution": [480, 856, 3], "filename": "bild220.jpg"}
{"click-Positions": [[479, 8], [317, 441]], "resolution": [480, 856, 3], "filename": "bild179.jpg"}
{"click-Positions": [[515, 7], [246, 474]], "resolution": [480, 856, 3], "filename": "bild90.jpg"}
{"click-Positions": [[538, 5], [426, 460]], "resolution": [480, 856, 3], "filename": "bild206.jpg"}
{"click-Positions": [[451, 10], [192, 473]], "resolution": [480, 856, 3], "filename": "bild116.jpg"}
{"click-Positions": [[317, 5], [299, 473]], "resolution": [480, 856, 3], "filename": "bild199.jpg"}
{"click-Positions": [[199, 6], [97, 474]], "resolution": [480, 856, 3], "filename": "bild258.jpg"}
{"click-Positions": [[210, 6], [112, 472]], "resolution": [480, 856, 3], "filename": "bild261.jpg"}
{"click-Positions": [[554, 7], [377, 470]], "resolution": [480, 856, 3], "filename": "bild43.jpg"}
{"click-Positions": [[283, 6], [101, 473]], "resolution": [480, 856, 3], "filename": "bild175.jpg"}
{"click-Positions": [[445, 10], [190, 474]], "resolution": [480, 856, 3], "filename": "bild103.jpg"}
{"click-Positions": [[326, 5], [154, 471]], "resolution": [480, 856, 3], "filename": "bild154.jpg"}
{"click-Positions": [[481, 8], [292, 474]], "resolution": [480, 856, 3], "filename": "bild183.jpg"}
{"click-Positions": [[337, 10], [231, 474]], "resolution": [480, 856, 3], "filename": "bild231.jpg"}
{"click-Positions": [[545, 9], [423, 457]], "resolution": [480, 856, 3], "filename": "bild20.jpg"}
{"click-Positions": [[515, 6], [237, 457]], "resolution": [480, 856, 3], "filename": "bild70.jpg"}
{"click-Positions": [[570, 9], [454, 454]], "resolution": [480, 856, 3], "filename": "bild19.jpg"}
{"click-Positions": [[431, 7], [181, 474]], "resolution": [480, 856, 3], "filename": "bild78.jpg"}
{"click-Positions": [[469, 6], [322, 469]], "resolution": [480, 856, 3], "filename": "bild194.jpg"}
{"click-Positions": [[356, 8], [214, 472]], "resolution": [480, 856, 3], "filename": "bild185.jpg"}
{"click-Positions": [[535, 11], [237, 475]], "resolution": [480, 856, 3], "filename": "bild76.jpg"}
{"click-Positions": [[528, 6], [383, 469]], "resolution": [480, 856, 3], "filename": "bild23.jpg"}
{"click-Positions": [[346, 4], [328, 450]], "resolution": [480, 856, 3], "filename": "bild122.jpg"}
{"click-Positions": [[529, 6], [348, 474]], "resolution": [480, 856, 3], "filename": "bild56.jpg"}
{"click-Positions": [[433, 9], [200, 474]], "resolution": [480, 856, 3], "filename": "bild86.jpg"}
{"click-Positions": [[207, 6], [105, 473]], "resolution": [480, 856, 3], "filename": "bild256.jpg"}
{"click-Positions": [], "resolution": [480, 856, 3], "filename": "bild165.jpg"}
{"click-Positions": [[465, 4], [215, 475]], "resolution": [480, 856, 3], "filename": "bild97.jpg"}
{"click-Positions": [[550, 5], [347, 475]], "resolution": [480, 856, 3], "filename": "bild58.jpg"}
{"click-Positions": [[311, 4], [311, 4]], "resolution": [480, 856, 3], "filename": "bild238.jpg"}
{"click-Positions": [[513, 6], [333, 456]], "resolution": [480, 856, 3], "filename": "bild34.jpg"}
{"click-Positions": [[561, 9], [366, 472]], "resolution": [480, 856, 3], "filename": "bild42.jpg"}
{"click-Positions": [[471, 8], [351, 469]], "resolution": [480, 856, 3], "filename": "bild203.jpg"}
{"click-Positions": [[114, 7], [5, 129]], "resolution": [480, 856, 3], "filename": "bild149.jpg"}
{"click-Positions": [[320, 7], [216, 477]], "resolution": [480, 856, 3], "filename": "bild237.jpg"}
{"click-Positions": [[291, 3], [278, 442]], "resolution": [480, 856, 3], "filename": "bild244.jpg"}
{"click-Positions": [[322, 2], [322, 2]], "resolution": [480, 856, 3], "filename": "bild236.jpg"}
{"click-Positions": [[815, 7], [772, 432]], "resolution": [480, 856, 3], "filename": "bild13.jpg"}
{"click-Positions": [[812, 6], [736, 406]], "resolution": [480, 856, 3], "filename": "bild14.jpg"}
{"click-Positions": [[416, 7], [389, 474]], "resolution": [480, 856, 3], "filename": "bild166.jpg"}
{"click-Positions": [[422, 8], [422, 8]], "resolution": [480, 856, 3], "filename": "bild197.jpg"}
{"click-Positions": [], "resolution": [480, 856, 3], "filename": "bild162.jpg"}
{"click-Positions": [[466, 6], [467, 6]], "resolution": [480, 856, 3], "filename": "bild117.jpg"}
{"click-Positions": [[597, 8], [361, 473]], "resolution": [480, 856, 3], "filename": "bild39.jpg"}
{"click-Positions": [[422, 2], [181, 476]], "resolution": [480, 856, 3], "filename": "bild85.jpg"}
{"click-Positions": [[830, 5], [808, 444]], "resolution": [480, 856, 3], "filename": "bild101.jpg"}
{"click-Positions": [[466, 5], [187, 474]], "resolution": [480, 856, 3], "filename": "bild110.jpg"}
{"click-Positions": [[309, 3], [292, 462]], "resolution": [480, 856, 3], "filename": "bild211.jpg"}
{"click-Positions": [[505, 6], [238, 473]], "resolution": [480, 856, 3], "filename": "bild100.jpg"}
{"click-Positions": [[231, 6], [135, 475]], "resolution": [480, 856, 3], "filename": "bild253.jpg"}
{"click-Positions": [[279, 10], [193, 474]], "resolution": [480, 856, 3], "filename": "bild251.jpg"}
{"click-Positions": [[450, 6], [176, 474]], "resolution": [480, 856, 3], "filename": "bild107.jpg"}
{"click-Positions": [[544, 7], [373, 471]], "resolution": [480, 856, 3], "filename": "bild45.jpg"}
{"click-Positions": [], "resolution": [480, 856, 3], "filename": "bild164.jpg"}
{"click-Positions": [[553, 6], [414, 433]], "resolution": [480, 856, 3], "filename": "bild24.jpg"}
{"click-Positions": [[421, 4], [395, 476]], "resolution": [480, 856, 3], "filename": "bild44.jpg"}
{"click-Positions": [[448, 4], [161, 474]], "resolution": [480, 856, 3], "filename": "bild135.jpg"}
{"click-Positions": [[403, 12], [301, 473]], "resolution": [480, 856, 3], "filename": "bild226.jpg"}
{"click-Positions": [[389, 7], [371, 408]], "resolution": [480, 856, 3], "filename": "bild11.jpg"}
{"click-Positions": [[529, 9], [441, 474]], "resolution": [480, 856, 3], "filename": "bild217.jpg"}
{"click-Positions": [[511, 12], [356, 473]], "resolution": [480, 856, 3], "filename": "bild182.jpg"}
{"click-Positions": [[208, 6], [108, 474]], "resolution": [480, 856, 3], "filename": "bild260.jpg"}
{"click-Positions": [[477, 6], [183, 474]], "resolution": [480, 856, 3], "filename": "bild109.jpg"}
{"click-Positions": [[626, 11], [420, 474]], "resolution": [480, 856, 3], "filename": "bild50.jpg"}
{"click-Positions": [[325, 3], [306, 464]], "resolution": [480, 856, 3], "filename": "bild188.jpg"}
{"click-Positions": [[545, 8], [368, 469]], "resolution": [480, 856, 3], "filename": "bild46.jpg"}
{"click-Positions": [[517, 6], [386, 474]], "resolution": [480, 856, 3], "filename": "bild204.jpg"}
{"click-Positions": [[348, 9], [330, 458]], "resolution": [480, 856, 3], "filename": "bild111.jpg"}
{"click-Positions": [[248, 6], [5, 374]], "resolution": [480, 856, 3], "filename": "bild63.jpg"}
{"click-Positions": [[326, 4], [307, 465]], "resolution": [480, 856, 3], "filename": "bild177.jpg"}
{"click-Positions": [[284, 4], [121, 474]], "resolution": [480, 856, 3], "filename": "bild174.jpg"}
{"click-Positions": [[433, 6], [186, 474]], "resolution": [480, 856, 3], "filename": "bild105.jpg"}
{"click-Positions": [[433, 8], [176, 472]], "resolution": [480, 856, 3], "filename": "bild115.jpg"}
{"click-Positions": [[420, 5], [136, 474]], "resolution": [480, 856, 3], "filename": "bild145.jpg"}
{"click-Positions": [[298, 4], [279, 469]], "resolution": [480, 856, 3], "filename": "bild233.jpg"}
{"click-Positions": [[567, 5], [306, 473]], "resolution": [480, 856, 3], "filename": "bild60.jpg"}
{"click-Positions": [[294, 8], [202, 474]], "resolution": [480, 856, 3], "filename": "bild250.jpg"}
{"click-Positions": [[349, 6], [243, 474]], "resolution": [480, 856, 3], "filename": "bild230.jpg"}
{"click-Positions": [[522, 8], [196, 472]], "resolution": [480, 856, 3], "filename": "bild69.jpg"}
{"click-Positions": [[499, 10], [334, 468]], "resolution": [480, 856, 3], "filename": "bild156.jpg"}
{"click-Positions": [[444, 10], [444, 10]], "resolution": [480, 856, 3], "filename": "bild120.jpg"}
{"click-Positions": [[457, 7], [170, 475]], "resolution": [480, 856, 3], "filename": "bild127.jpg"}
{"click-Positions": [], "resolution": [480, 856, 3], "filename": "bild73.jpg"}
{"click-Positions": [[460, 4], [300, 468]], "resolution": [480, 856, 3], "filename": "bild193.jpg"}
{"click-Positions": [[422, 6], [166, 473]], "resolution": [480, 856, 3], "filename": "bild123.jpg"}
{"click-Positions": [[659, 10], [482, 473]], "resolution": [480, 856, 3], "filename": "bild29.jpg"}
{"click-Positions": [[362, 6], [344, 457]], "resolution": [480, 856, 3], "filename": "bild77.jpg"}
{"click-Positions": [[545, 9], [345, 474]], "resolution": [480, 856, 3], "filename": "bild53.jpg"}
{"click-Positions": [], "resolution": [480, 856, 3], "filename": "bild150.jpg"}
{"click-Positions": [[274, 7], [180, 473]], "resolution": [480, 856, 3], "filename": "bild246.jpg"}
{"click-Positions": [[520, 6], [394, 333]], "resolution": [480, 856, 3], "filename": "bild168.jpg"}
{"click-Positions": [[380, 5], [362, 458]], "resolution": [480, 856, 3], "filename": "bild22.jpg"}
{"click-Positions": [[445, 9], [158, 474]], "resolution": [480, 856, 3], "filename": "bild134.jpg"}
{"click-Positions": [[287, 6], [189, 474]], "resolution": [480, 856, 3], "filename": "bild242.jpg"}
{"click-Positions": [[428, 6], [161, 475]], "resolution": [480, 856, 3], "filename": "bild129.jpg"}
{"click-Positions": [[418, 7], [183, 474]], "resolution": [480, 856, 3], "filename": "bild79.jpg"}
{"click-Positions": [[400, 6], [205, 470]], "resolution": [480, 856, 3], "filename": "bild190.jpg"}
{"click-Positions": [[438, 6], [162, 473]], "resolution": [480, 856, 3], "filename": "bild125.jpg"}
{"click-Positions": [[478, 6], [478, 6]], "resolution": [480, 856, 3], "filename": "bild93.jpg"}
{"click-Positions": [[371, 5], [353, 426]], "resolution": [480, 856, 3], "filename": "bild55.jpg"}
{"click-Positions": [[279, 6], [179, 476]], "resolution": [480, 856, 3], "filename": "bild243.jpg"}
{"click-Positions": [[677, 3], [509, 473]], "resolution": [480, 856, 3], "filename": "bild28.jpg"}
{"click-Positions": [[285, 6], [268, 460]], "resolution": [480, 856, 3], "filename": "bild255.jpg"}
{"click-Positions": [[576, 8], [362, 438]], "resolution": [480, 856, 3], "filename": "bild41.jpg"}
{"click-Positions": [[431, 8], [181, 472]], "resolution": [480, 856, 3], "filename": "bild82.jpg"}
{"click-Positions": [[678, 7], [509, 471]], "resolution": [480, 856, 3], "filename": "bild27.jpg"}
{"click-Positions": [[69, 9], [6, 120]], "resolution": [480, 856, 3], "filename": "bild161.jpg"}
{"click-Positions": [[400, 10], [400, 10]], "resolution": [480, 856, 3], "filename": "bild139.jpg"}
{"click-Positions": [[457, 6], [239, 472]], "resolution": [480, 856, 3], "filename": "bild94.jpg"}
{"click-Positions": [[303, 2], [303, 2]], "resolution": [480, 856, 3], "filename": "bild222.jpg"}
{"click-Positions": [[399, 10], [400, 10]], "resolution": [480, 856, 3], "filename": "bild71.jpg"}
{"click-Positions": [[623, 6], [445, 473]], "resolution": [480, 856, 3], "filename": "bild25.jpg"}
{"click-Positions": [[18, 6], [3, 33]], "resolution": [480, 856, 3], "filename": "bild152.jpg"}
{"click-Positions": [[351, 6], [332, 460]], "resolution": [480, 856, 3], "filename": "bild99.jpg"}
{"click-Positions": [[502, 9], [239, 474]], "resolution": [480, 856, 3], "filename": "bild98.jpg"}
{"click-Positions": [[500, 6], [501, 6]], "resolution": [480, 856, 3], "filename": "bild213.jpg"}
{"click-Positions": [[506, 7], [403, 474]], "resolution": [480, 856, 3], "filename": "bild214.jpg"}
{"click-Positions": [[292, 6], [292, 6]], "resolution": [480, 856, 3], "filename": "bild249.jpg"}
{"click-Positions": [[463, 10], [172, 474]], "resolution": [480, 856, 3], "filename": "bild119.jpg"}
{"click-Positions": [[375, 4], [282, 470]], "resolution": [480, 856, 3], "filename": "bild228.jpg"}
{"click-Positions": [[313, 9], [219, 474]], "resolution": [480, 856, 3], "filename": "bild234.jpg"}
